{
	"picarto":{
		"Site": "https://picarto.tv",
		"ClientID": "594d822e-d09a-40e3-8026-8b24695a20a8",
		"AuthenticationAPI": "https://oauth.picarto.tv/authorize",
		"TokenAPI": "https://oauth.picarto.tv/token",
		"Scopes": ["readpriv", "readpub"]
	},
	"piczel":{
		"Site": "https://piczel.tv",
		"CookieDomain": "https://piczel.tv/",
		"CookieName": "authHeaders"
	},
	"twitch":{
		"Site": "https://twitch.tv",
		"ClientID": "dtv6kthgiel4kqfrnaqmtlgig7xztj",
		"AuthenticationAPI": "https://id.twitch.tv/oauth2/authorize",
		"Scopes": ["user:read:follows"],
		"PKCE": false
	},
	"youtube":{
		"Site": "https://youtube.com",
		"ClientID": "463633408812-06gm6hp78drr5djcdee1j5s0r7t5j0bp.apps.googleusercontent.com",
		"AuthenticationAPI": "https://accounts.google.com/o/oauth2/v2/auth",
		"TokenAPI": "https://oauth2.googleapis.com/token",
		"Scopes": ["https://www.googleapis.com/auth/youtube.readonly"]
	}
}